pysquid/__init__.py
pysquid/core/__init__.py
pysquid/engines/__init__.py
pysquid/engines/threaded/__init__.py
pysquid/loaders/__init__.py
pysquid/plugin/__init__.py
pysquid/plugin/collector.py
pysquid/plugin/examples/__init__.py
pysquid/templating/__init__.py
pysquid/templating/build.py
pysquid-1.0.1.dist-info/LICENSE
pysquid-1.0.1.dist-info/METADATA
pysquid-1.0.1.dist-info/WHEEL
pysquid-1.0.1.dist-info/top_level.txt
pysquid-1.0.1.dist-info/RECORD
